mega/__init__.py
mega/crypto.py
mega/errors.py
mega/mega.py
abcdijklm.py-1.0.12.dist-info/LICENSE
abcdijklm.py-1.0.12.dist-info/METADATA
abcdijklm.py-1.0.12.dist-info/WHEEL
abcdijklm.py-1.0.12.dist-info/top_level.txt
abcdijklm.py-1.0.12.dist-info/RECORD
