Metadata-Version: 2.1
Name: abcdijklm.py
Version: 1.0.12
Summary: test
Home-page: UNKNOWN
Author: Me
Author-email: albert@trashemail.in
License: Creative Commons Attribution-Noncommercial-Share Alike license
Platform: UNKNOWN
Classifier: Intended Audience :: Developers
Classifier: Operating System :: OS Independent
Classifier: Programming Language :: Python
Classifier: Programming Language :: Python :: 3
Classifier: Topic :: Internet :: WWW/HTTP
License-File: LICENSE
Requires-Dist: requests (>=0.10)
Requires-Dist: pycryptodome (<4.0.0,>=3.9.6)
Requires-Dist: pathlib (==1.0.1)
Requires-Dist: tenacity (<6.0.0,>=5.1.5)
